habitipy/__init__.py
habitipy/aio.py
habitipy/api.py
habitipy/apidoc.txt
habitipy/async.py
habitipy/cli.py
habitipy/util.py
habitipy/i18n/ru/LC_MESSAGES/habitipy.mo
habitipy-0.3.3.dist-info/LICENSE.txt
habitipy-0.3.3.dist-info/METADATA
habitipy-0.3.3.dist-info/WHEEL
habitipy-0.3.3.dist-info/entry_points.txt
habitipy-0.3.3.dist-info/top_level.txt
habitipy-0.3.3.dist-info/RECORD
