Metadata-Version: 2.1
Name: habitipy
Version: 0.3.3
Summary: tools and library for Habitica restful API (http://habitica.com)
Home-page: https://github.com/ASMfreaK/habitipy
Author: Pavel Pletenev
Author-email: cpp.create@gmail.com
License: MIT
Classifier: License :: OSI Approved :: MIT License
Classifier: Development Status :: 4 - Beta
Classifier: Programming Language :: Python :: 3.5
Classifier: Programming Language :: Python :: 3.6
Classifier: Topic :: Software Development :: Libraries :: Python Modules
Classifier: Topic :: Utilities
Classifier: Topic :: Games/Entertainment
Classifier: Topic :: Internet
Classifier: Environment :: Console
Classifier: Operating System :: OS Independent
Classifier: Intended Audience :: Developers
Classifier: Intended Audience :: End Users/Desktop
License-File: LICENSE.txt
Requires-Dist: plumbum
Requires-Dist: requests
Requires-Dist: setuptools
Provides-Extra: aio
Requires-Dist: aiohttp; extra == "aio"
Provides-Extra: emoji
Requires-Dist: emoji; extra == "emoji"
